{"is_source_file": false, "format": null, "description": "", "external_files": [], "external_methods": [], "published": [], "classes": [], "methods": [], "calls": [], "search-terms": ["Create React App", "manifest.json", "short_name", "icons", "start_url", "display", "theme_color", "background_color"], "state": 2, "file_id": 2, "knowledge_revision": 16, "git_revision": "ab5a24376e51fb4aa25a8859a22cebf5328644d6", "hash": "d9d975cebe2ec20b6c652e1e4c12ccf0", "format-version": 4, "code-base-name": "recipes_frontend", "filename": "recipes_frontend/public/manifest.json", "revision_history": [{"16": "ab5a24376e51fb4aa25a8859a22cebf5328644d6"}]}